harzvatool/Tools.py
harzvatool/__init__.py
harzvatool/parrots_wrapper.py
harzvatool/tools.py
harzvatool/until.py
harzvatool-2.6.dist-info/LICENSE.txt
harzvatool-2.6.dist-info/METADATA
harzvatool-2.6.dist-info/WHEEL
harzvatool-2.6.dist-info/top_level.txt
harzvatool-2.6.dist-info/RECORD
