Metadata-Version: 2.1
Name: harzvatool
Version: 2.6
Summary: harzva's package
Home-page: https://github.com/Harzva/harzvatool/
Author: harzva
Author-email: 626609967@qq.com
License: Apache License v1
Platform: UNKNOWN
Classifier: Programming Language :: Python
Classifier: Operating System :: POSIX :: Linux
Classifier: Operating System :: Unix
Classifier: Programming Language :: Python
License-File: LICENSE.txt
Requires-Dist: torch
